{
  "db": {
    "name": "db",
    "connector": "memory"
  },
  "mongoDs": {
    "name": "mongoDs",
    "connector": "memory"
  },
  "userDs": {
    "name": "userDs",
    "connector": "memory"
  },
  "sendgridDs": {
    "name": "sendgridDs",
    "connector": "memory"
  },
  "filesDs": {
    "name": "filesDs",
    "connector": "memory"
  },
  "pushDs": {
    "name": "pushDs",
    "connector": "loopback-component-push",
    "installation": "Installation",
    "notification": "Notification",
    "application": "Application"
  }
}
